calculator_kazbad/__init__.py
calculator_kazbad/calculator.py
calculator_kazbad-0.2.dist-info/WHEEL
calculator_kazbad-0.2.dist-info/METADATA
calculator_kazbad-0.2.dist-info/RECORD
