Metadata-Version: 2.1
Name: calculator_kazbad
Version: 0.2
Summary: A simple Calculator package
Author-email: Kazimieras <dr.kazimieras@yahoo.com>
Requires-Python: >=3.7
Classifier: Programming Language :: Python :: 3
Classifier: License :: OSI Approved :: MIT License
Classifier: Operating System :: OS Independent
Project-URL: Homepage, https://github.com/Dr-KBa/Calculator
